{
    "code": "a075357353daffa94d17f2ab3043d8bd85059f1d",
    "title": "Ủy ban xã không cho dựng rạp cưới vì chưa đăng ký kết hôn",
    "url": "http://vnexpress.net/tin-tuc/phap-luat/tu-van/uy-ban-xa-khong-cho-dung-rap-cuoi-vi-chua-dang-ky-ket-hon-3511489.html",
    "labels": "vnexpress/Pháp luật/Tư vấn",
    "content": "\n\tChúng tôi dự định tổ chức đám cưới trước rồi mới đăng ký kết hôn sau. Hôm tổ chức đám cưới, Ủy ban xã đến kiểm tra giấy đăng ký kết hôn của tôi và không cho phép dựng rạp vì lý do chưa có đăng ký kết hôn. Tôi xin hỏi chính quyền xã có quyền như vậy không? Tổ chức hôn lễ và đăng ký kết hôn, việc gì nên làm trước?\nHuyền Trang\nLuật sư trả lời\n>>Sau cưới bao lâu phải đăng ký kết hôn?\n>>Mất giấy đăng ký kết hôn có bị coi không còn là vợ chồng?",
    "image_url": "http://img.f29.vnecdn.net/2016/12/10/minhhoadangkykethon-1481339756_180x108.jpg",
    "date": "2016-12-11T01:56:52Z"
}