{
    "code": "f309f066b2e65737489f938e3cfbcfb1aca0e06a",
    "title": "Giám đốc ở Sài Gòn ôm gần 40 tỷ đồng bỏ trốn",
    "url": "http://vnexpress.net/tin-tuc/phap-luat/giam-doc-o-sai-gon-om-gan-40-ty-dong-bo-tron-3512507.html",
    "labels": "vnexpress/Pháp luật",
    "content": "\n\tPhòng Cảnh sát điều tra tội phạm về Kinh tế và Tham nhũng (PC46) Công an TP HCM) đêm 12/12 bắt Trần Quốc Bảo (29 tuổi, giám đốc Công ty TNHH Dịch vụ viễn thông tin học Miền Nam) theo lệnh truy nã về hành vi Lạm dụng tín nhiệm chiếm đoạt tài sản.\n\tTheo điều tra, công ty của Bảo được thành lập tháng 6/2011 tại quận Gò Vấp nhưng chỉ hoạt động cầm chừng. Cuối năm đó cơ quan chức năng kiểm tra, phát hiện công ty đã ngưng hoạt động và giám đốc Bảo không còn ở nơi cư trú.\n\tCó 6 người sau đó đã tố cáo đã đặt cọc cho Bảo hơn 38 tỷ đồng để mua thẻ cào điện thoại nhưng anh ta bỏ trốn, không thực hiện hợp đồng. Giữa năm 2014, Bảo bị truy nã về tội Lạm dụng tín nhiệm chiếm đoạt tài sản.\n\tCảnh sát bắt được Bảo khi hắn lẩn trốn ở Đà Nẵng.\nQuốc Thắng",
    "image_url": "http://img.f29.vnecdn.net/2016/12/13/giamdoc-4865-1481590197_180x108.jpg",
    "date": "2016-12-13T08:53:40Z"
}