{
    "code": "dd0cad3ea7fefcdd36c51654e961b411c893b748",
    "title": "Bill Gates cùng các \"trùm công nghệ\" đầu tư 1 tỷ USD cho công nghệ sạch",
    "url": "http://vietbao.vn/Cong-nghe/Bill-Gates-cung-cac-trum-cong-nghe-dau-tu-1-ty-USD-cho-cong-nghe-sach/223146796/217/",
    "labels": "vietbao/Công Nghệ/Tin Tổng Hợp",
    "content": "Tỷ phú Bill Gates cùng một số lãnh đạo cao cấp khác sẽ đầu tư 1 tỷ USD vào quỹ ủng hộ công nghệ năng lượng sạch và xử lý biến đổi khí hậu.Tỷ phú Bill GatesHôm 12/12, Gates ra mắt quỹ Breakthrough Energy Ventures cùng các doanh nhân tỷ phú khác như CEO Facebook Mark Zuckerberg, Chủ tịch Alibaba Jack Ma và CEO Amazon Jeff Bezos.Theo tuyên bố của nhóm đầu tư Breakthrough Energy Coalition, quỹ có mục đích tăng cường tài chính cho các nghiên cứu năng lượng mới và giảm hiệu ứng khí thải nhà kính để đáp ứng các mục tiêu đặt ra trong Thỏa thuận chung Paris về biến đổi khí hậu (COP21).Nó đánh dấu khoản đầu tư lớn đầu tiên của liên minh kể từ tháng 12/2015 nhằm khích lệ nghiên cứu, phát triển và triển khai công nghệ năng lượng sạch.Trả lời tạp chí Quartz, Gates cho biết: “Chúng ta cần năng lượng sạch, đáng tin cậy, không phát sinh khí thải cho tương lai và để làm được điều đó, chúng ta cần mô hình khác biệt để đầu tư vào ý tưởng hay và chuyển chúng từ phòng thí nghiệm ra thị trường”.Năm ngoái, Gates cũng trợ giúp mở liên doanh tập trung vào đầu tư công nghệ sạch mới, rủi ro, thường phải đối đầu với nhiều chướng ngại vật trên đường thương mại hóa.Du Lam (Theo Reuters)Du Lam (Theo Reuters)",
    "image_url": "http://a9.vietbao.vn/images/vn999/223/2016/12/vietnam_20161213-c-225-c-quot-tr-249-m-c-244-ng-nghe-quot-dau-tu-1-ty-usd-cho-c-244-ng-nghe-sach-1.jpg",
    "date": "2016-12-13T08:24:28Z"
}