{
    "code": "319e3cb4b6c4410f4594a253b40a94fd4f71ad92",
    "title": "Quảng Ngãi ban hành quy định tuyển sinh vào lớp 10 THPT",
    "url": "http://vietbao.vn/Giao-duc/Quang-Ngai-ban-hanh-quy-dinh-tuyen-sinh-vao-lop-10-THPT/442670872/202/",
    "labels": "vietbao/Giáo Dục/Tin Giáo Dục",
    "content": "GD&TĐ - Sở GD&ĐT Quãng Ngãi công bố quy định tuyển sinh vào lớp 10 THPT. Theo đó, việc tuyển sinh THPT trên địa bàn được tổ chức theo một trong ba phương thức sau:Xét tuyển: Dựa trên kết quả rèn luyện, học tập của 4 năm học ở THCS của đối tượng tuyển sinh, nếu lưu ban lớp nào thì lấy kết quả năm học lại của lớp đó;Thi tuyển; kết hợp thi tuyển với xét tuyển.Tuyển thẳng vào THPT các đối tượng sau đây: Học sinh trường phổ thông dân tộc nội trú; học sinh là người dân tộc rất ít người theo quy định; học sinh khuyết tật; học sinh đạt giải cấp quốc gia trở lên về văn hóa, văn nghệ, thể dục thể thao, thi khoa học kĩ thuật dành cho học sinh trung học.Sở GD&ĐT cũng quy định chế độ ưu tiên (không áp dụng cho tuyển sinh vào lớp 10 THPT chuyên) với các mức ưu tiên, khuyến khích: Cộng 3 điểm, 2 điểm, 1,5 điểm, 1 điểm, 0,5 điểm tương ứng với đối tượng cụ thể.Về thi tuyển vào lớp 10 trường THPT DTNT: Thi viết 2 môn Toán và Ngữ văn; thi vào lớp 10 trường THPT 3 môn Toán, Ngữ văn và môn thứ 3; thi vào lớp 10 trường THPT chuyên với 4 môn Toán, Ngữ văn, Ngoại ngữ và môn chuyên; thi vào lớp 10 chuyên Tin học, thí sinh thi môn Toán (bài thi chuyên).Học sinh đăng kí nguyện vọng và nộp hồ sơ tuyển sinh tại trường THPT có nguyện vọng 1. Mỗi học sinh được quyền chọn 2 nguyện vọng khi dự tuyển vào lớp 10 theo quy định của Sở GD&ĐT: Nguyện vọng 1 dự tuyển vào 1 trường THPT công lập; nguyện vọng 2 dự tuyển vào 1 trường THPT công lập thứ hai theo quy định hoặc trường THPT ngoài công lập…Lập Phương",
    "image_url": "",
    "date": "2016-12-10T17:06:00Z"
}