{
    "code": "7d6371989b45c5be438598dcdc7bf73bd2380a06",
    "title": "Nguy cơ tai nạn khi trẻ em chơi bên đường một mình",
    "url": "http://dantri.com.vn/o-to-xe-may/nguy-co-tai-nan-khi-tre-em-choi-ben-duong-mot-minh-20161206120314856.htm",
    "labels": "Dân trí/Ô tô - Xe máy",
    "content": "\nDân trí Đoạn clip trên mũ bảo hiểm người đi xe máy ghi lại một tình huống giao thông thực sự nguy hiểm khi đứa bé khoảng 3 tuổi đang chơi một mình bên đường bỗng chạy phắt sang đường...\nKhi trẻ em chơi đùa gần đường giao thông, nhất thiết cần phải có người lớn trông chừng bởi khi còn quá bé, trẻ sẽ không đủ năng lực hành vi để biết thế nào là nguy hiểm.Nguồn: UB An toàn Giao thông QG ",
    "image_url": "https://dantri4.vcmedia.vn/zoom/80_50/18be5f307b/2016/12/06/cover-1480999305008.gif",
    "date": "2016-12-06T12:05:00Z"
}