{
    "code": "dff53b488b35d52d42cd10452066418237fbdf09",
    "title": "Lái xe thế nào cho tiết kiệm nhiên liệu?",
    "url": "http://dantri.com.vn/o-to-xe-may/lai-xe-the-nao-cho-tiet-kiem-nhien-lieu-20161209044012652.htm",
    "labels": "Dân trí/Ô tô - Xe máy",
    "content": "\nDân trí Thế nào là người biết lái xe? Câu trả lời không chỉ đơn thuần là việc lên xe và phóng đi như một cơn lốc. Xử lí tình huống tốt, phản xạ nhanh nhạy và đặc biệt là có hiệu quả tiêu thụ nhiên liệu cao... mới là những vấn đề đáng quan tâm.\nTrên thực tế, với các kỹ năng xử lí tình huống hay có phản xạ tốt khi lái xe, bạn phải rèn luyện, thì với việc lái xe tiết kiệm nhiên liệu, có nhiều cách đơn giản để bạn thực hiện ngay lập tức, không đòi hỏi kỹ thuật gì cao siêu.  Việc lái xe tiết kiệm nhiên liệu không chỉ giúp bạn tránh phải \"móc ví\" quá nhiều; mà hơn thế, còn có ý nghĩa bảo vệ môi trường.Đồ hoạ: Vũ Toản  ",
    "image_url": "https://dantri4.vcmedia.vn/zoom/80_50/18be5f307b/2016/12/08/anh-bia-1481216083239.jpg",
    "date": "2016-12-09T07:30:00Z"
}