{
    "code": "6104252423e26b52f1721f5e0eed60219c2513ff",
    "title": "Hồ Quỳnh Hương bất ngờ thổ lộ mong ước về gia đình nhỏ",
    "url": "http://dantri.com.vn/giai-tri/ho-quynh-huong-bat-ngo-tho-lo-mong-uoc-ve-gia-dinh-nho-20161210173243616.htm",
    "labels": "Dân trí/Giải trí",
    "content": "\nDân trí Mặc dù đã thành danh, vô cùng nổi tiếng nhưng vẫn có cuộc sống độc thân và cũng hiếm khi chia sẻ về chuyện tình cảm riêng tư. Cũng từng trả lời phỏng vấn, có thể chọn cuộc sống độc thân, ca sĩ Hồ Quỳnh Hương bất ngờ thổ lộ mình cũng đang nghĩ về gia đình riêng trong một chương trình ca nhạc vừa lên sóng.\r\nTối qua (9/12), khi tham gia chương trình Thay lời muốn nói với chủ đề Hạnh phúc nơi này, giọng ca “Anh” bất ngờ chia sẻ ước mơ về gia đình của riêng mình.Điều này khiến người hâm mộ cảm thấy bất ngờ và cũng có phần đồng cảm. Bởi mặc dù là một trong những mỹ nhân Vbiz sớm thành công trong con đường ca hát, nhưng đến nay, dù đã ở ngưỡng U40, Hồ Quỳnh Hương vẫn một mình.Hoàng Yến Chibi được nhiều khán giả trẻ yêu thích bởi ngoại hình dễ thương và giọng hát trong trẻo. Vừa đón sinh nhật ở tuổi 22, giọng ca “Ngây ngô” đã tất bật chạy show dịp cuối năm. Trong chương trình, nữ ca sĩ solo đầy da diết nhạc phẩm \"Lời con hứa\" với sự hỗ trợ của guitar Hoàng Minh.Băng ChâuẢnh: Hiếu Nguyễn",
    "image_url": "https://dantri4.vcmedia.vn/zoom/80_50/b78705f365/2016/12/10/img-9486-1481354525460.jpg",
    "date": "2016-12-10T17:33:00Z"
}